README.rst
setup.py
escaperoom/__init__.py
escaperoom/__version__.py
escaperoom/reader.py
escaperoom/room.py
escaperoom/server.py
escaperoom.egg-info/PKG-INFO
escaperoom.egg-info/SOURCES.txt
escaperoom.egg-info/dependency_links.txt
escaperoom.egg-info/entry_points.txt
escaperoom.egg-info/requires.txt
escaperoom.egg-info/top_level.txt