Metadata-Version: 1.1
Name: escaperoom
Version: 0.0.3
Summary: Flask based microframework to generate virtual escape room.
Home-page: https://github.com/csurfer/escaperoom
Author: Vishwas B Sharma
Author-email: sharma.vishwas88@gmail.com
License: MIT
Keywords: Generate virtual escape rooms from JSON config without a single line of code.
Platform: UNKNOWN
Classifier: Intended Audience :: Developers
Classifier: License :: OSI Approved :: MIT License
Classifier: Development Status :: 3 - Alpha
Classifier: Operating System :: POSIX
Classifier: Programming Language :: Python :: 3.8
Classifier: Topic :: Games/Entertainment
